tquota/__init__.py
tquota/quota.py
tquota-0.0.3.dist-info/LICENSE
tquota-0.0.3.dist-info/METADATA
tquota-0.0.3.dist-info/WHEEL
tquota-0.0.3.dist-info/top_level.txt
tquota-0.0.3.dist-info/RECORD
