Metadata-Version: 2.1
Name: tquota
Version: 0.0.3
Summary: A lightweight processing timer module for quota-based cloud environments.
Home-page: https://github.com/aljbri/tquota
Author: Abdussalam Aljbri
Author-email: Abdussalam Aljbri <mr.aljbri@gmail.com>
Maintainer-email: Abdussalam Aljbri <mr.aljbri@gmail.com>
License: MIT License
Project-URL: Homepage, https://github.com/aljbri/tquota/
Project-URL: Documentation, https://aljbri.github.io/tquota/
Project-URL: Repository, https://github.com/aljbri/tquota/
Project-URL: Issues, https://github.com/aljbri/tquota/issues
Keywords: quota,cloud,timer,kaggle,colab,session,management,monitor
Classifier: Programming Language :: Python :: 2.7
Classifier: Programming Language :: Python :: 3.0
Classifier: Programming Language :: Python :: 3
Classifier: License :: OSI Approved :: MIT License
Classifier: Operating System :: OS Independent
Requires-Python: >=2.7, <4
License-File: LICENSE
